{"title":"Nulled WHMCS for webhosts","uid":7359119,"size":8679125,"categoryP":"other","categoryS":"other","magnet":"?xt=urn:btih:03e6754db7836c6badd702e9b43700e1fe3e9ea7&amp;dn=Nulled+WHMCS+for+webhosts&amp;tr=udp%3A%2F%2Ftracker.openbittorrent.com%3A80&amp;tr=udp%3A%2F%2Fopen.demonii.com%3A1337&amp;tr=udp%3A%2F%2Ftracker.coppersurfer.tk%3A6969&amp;tr=udp%3A%2F%2Fexodus.desync.com%3A6969","seeders":0,"leechers":1,"uploader":"Cometfire","files":1,"time":1339886159,"description":"This is a nulled version of WHMCS.\nIf you want to have your own webhost, then get this script.\nThere are no backdoors.\nVirus scan:  &lt;a href=&quot;\nhttps://www.virustotal.com/file/db2f3327fc8800be4079ce9782f7ffad8b293a86f1d71d3d63be8259a83d4a9b/analysis/&quot; rel=&quot;nofollow&quot; target=&quot;_NEW&quot;&gt;\nhttps://www.virustotal.com/file/db2f3327fc8800be4079ce9782f7ffad8b293a86f1d71d3d63be8259a83d4a9b/analysis/&lt;/a&gt;\nHave fun with making tons of money.\t","torrent":{"xt":"urn:btih:03e6754db7836c6badd702e9b43700e1fe3e9ea7","amp;dn":"Nulled+WHMCS+for+webhosts","amp;tr":["udp%3A%2F%2Ftracker.openbittorrent.com%3A80","udp%3A%2F%2Fopen.demonii.com%3A1337","udp%3A%2F%2Ftracker.coppersurfer.tk%3A6969","udp%3A%2F%2Fexodus.desync.com%3A6969"],"infoHash":"03e6754db7836c6badd702e9b43700e1fe3e9ea7","infoHashBuffer":{"type":"Buffer","data":[3,230,117,77,183,131,108,107,173,215,2,233,180,55,0,225,254,62,158,167]},"announce":[],"urlList":[]}}