{"title":"BigWetButts - Julie Cash - The Million Dollar Ass.mp4","uid":7377253,"size":314476237,"categoryP":"porn","categoryS":"movie_clips","magnet":"?xt=urn:btih:0c3c6d613c48d3a87cb49e5fe9cb44435b0182e9&amp;dn=BigWetButts+-+Julie+Cash+-+The+Million+Dollar+Ass.mp4&amp;tr=udp%3A%2F%2Ftracker.openbittorrent.com%3A80&amp;tr=udp%3A%2F%2Fopen.demonii.com%3A1337&amp;tr=udp%3A%2F%2Ftracker.coppersurfer.tk%3A6969&amp;tr=udp%3A%2F%2Fexodus.desync.com%3A6969","seeders":0,"leechers":1,"uploader":"SplashPt","files":-1,"time":1340394368,"description":"BigWetButts - Julie Cash - The Million Dollar Ass.mp4\n\nDescription: \nJulie Cash's ass is worth a million bucks and Erik Everhard plans on milking that ass for every cent its worth.\n\nResolution: 854x480\n\nRun Time: 00:35:17\n\nTags: Big Tits, Blonde, Facial, Gonzo, Tattoo, Anal, Oil\n\nScreens:\n &lt;a href=&quot;\nhttp://postimg.me/viewer.php?file=8skrneimdpmp6znnm36x.jpg&quot; rel=&quot;nofollow&quot; target=&quot;_NEW&quot;&gt;\nhttp://postimg.me/viewer.php?file=8skrneimdpmp6znnm36x.jpg&lt;/a&gt;\n &lt;a href=&quot;\nhttp://postimg.me/viewer.php?file=bst0wzev9uhccmyntx28.jpg&quot; rel=&quot;nofollow&quot; target=&quot;_NEW&quot;&gt;\nhttp://postimg.me/viewer.php?file=bst0wzev9uhccmyntx28.jpg&lt;/a&gt;","torrent":{"xt":"urn:btih:0c3c6d613c48d3a87cb49e5fe9cb44435b0182e9","amp;dn":"BigWetButts+-+Julie+Cash+-+The+Million+Dollar+Ass.mp4","amp;tr":["udp%3A%2F%2Ftracker.openbittorrent.com%3A80","udp%3A%2F%2Fopen.demonii.com%3A1337","udp%3A%2F%2Ftracker.coppersurfer.tk%3A6969","udp%3A%2F%2Fexodus.desync.com%3A6969"],"infoHash":"0c3c6d613c48d3a87cb49e5fe9cb44435b0182e9","infoHashBuffer":{"type":"Buffer","data":[12,60,109,97,60,72,211,168,124,180,158,95,233,203,68,67,91,1,130,233]},"announce":[],"urlList":[]}}