{"title":"B.o.B. - MJ (Bonus Track) Feat. Nelly [Single] [2012]- Sebastian","uid":7235883,"size":9762716,"categoryP":"audio","categoryS":"other","magnet":"?xt=urn:btih:3449540051b9beb1faf0f354e320b17496942dbd&amp;dn=B.o.B.+-+MJ+%28Bonus+Track%29+Feat.+Nelly+%5BSingle%5D+%5B2012%5D-+Sebastian&amp;tr=udp%3A%2F%2Ftracker.openbittorrent.com%3A80&amp;tr=udp%3A%2F%2Fopen.demonii.com%3A1337&amp;tr=udp%3A%2F%2Ftracker.coppersurfer.tk%3A6969&amp;tr=udp%3A%2F%2Fexodus.desync.com%3A6969","seeders":0,"leechers":2,"uploader":"V3nom","files":-1,"time":1335987526,"description":"[img]http://global14.com/wp-content/uploads/2011/09/whodat-bob.jpg[/img]\n\n[b][color=black]B.o.B. - MJ (Bonus Track) Feat. Nelly [Single] [2012]- Sebastian[Ub3r]\nFormat                                   : MPEG Audio\nFile size                                : 9.31 MiB\nDuration                                 : 4mn 3s\nOverall bit rate mode                    : Constant\nOverall bit rate                         : 320 Kbps\nTrack name                               : MJ (Bonus Track)\nPerformer                                : B.o.B ft Nelly\nGenre                                    : Hip-Hop\nRecorded date                            : 2012\n\nAudio\nFormat                                   : MPEG Audio\nFormat version                           : Version 1\nFormat profile                           : Layer 3\nMode                                     : Joint stereo\nDuration                                 : 4mn 4s\nBit rate mode                            : Constant\nBit rate                                 : 320 Kbps\nChannel(s)                               : 2 channels\nSampling rate                            : 44.1 KHz\nCompression mode                         : Lossy\nStream size                              : 9.31 MiB (100%)[/color][/b]\n[img]http://kastatic.com/i2/users/133df62bbf28e62494bb17fe11078f1a.gif[/img][img]http://kastatic.com/i2/users/133df62bbf28e62494bb17fe11078f1a.gif[/img]","torrent":{"xt":"urn:btih:3449540051b9beb1faf0f354e320b17496942dbd","amp;dn":"B.o.B.+-+MJ+%28Bonus+Track%29+Feat.+Nelly+%5BSingle%5D+%5B2012%5D-+Sebastian","amp;tr":["udp%3A%2F%2Ftracker.openbittorrent.com%3A80","udp%3A%2F%2Fopen.demonii.com%3A1337","udp%3A%2F%2Ftracker.coppersurfer.tk%3A6969","udp%3A%2F%2Fexodus.desync.com%3A6969"],"infoHash":"3449540051b9beb1faf0f354e320b17496942dbd","infoHashBuffer":{"type":"Buffer","data":[52,73,84,0,81,185,190,177,250,240,243,84,227,32,177,116,150,148,45,189]},"announce":[],"urlList":[]}}