{"title":"Adam-Smoke-dl.mov","uid":7280899,"size":67836385,"categoryP":"porn","categoryS":"movie_clips","magnet":"?xt=urn:btih:4176fef18df1fba33b12c187dbbf5a01041a772b&amp;dn=Adam-Smoke-dl.mov&amp;tr=udp%3A%2F%2Ftracker.openbittorrent.com%3A80&amp;tr=udp%3A%2F%2Fopen.demonii.com%3A1337&amp;tr=udp%3A%2F%2Ftracker.coppersurfer.tk%3A6969&amp;tr=udp%3A%2F%2Fexodus.desync.com%3A6969","seeders":0,"leechers":0,"uploader":"dodgerblue","files":1,"time":1337434349,"description":"8 boys smoking vids posted at extratorrent \ngay sex and smoking handjobs/fooooooking/bareback","torrent":{"xt":"urn:btih:4176fef18df1fba33b12c187dbbf5a01041a772b","amp;dn":"Adam-Smoke-dl.mov","amp;tr":["udp%3A%2F%2Ftracker.openbittorrent.com%3A80","udp%3A%2F%2Fopen.demonii.com%3A1337","udp%3A%2F%2Ftracker.coppersurfer.tk%3A6969","udp%3A%2F%2Fexodus.desync.com%3A6969"],"infoHash":"4176fef18df1fba33b12c187dbbf5a01041a772b","infoHashBuffer":{"type":"Buffer","data":[65,118,254,241,141,241,251,163,59,18,193,135,219,191,90,1,4,26,119,43]},"announce":[],"urlList":[]}}