{"title":"ShesAFreak - Ashley Reeves","uid":6670904,"size":359340975,"categoryP":"porn","categoryS":"movie_clips","magnet":"?xt=urn:btih:4a3ae397d795b170e2e911cf230e0400be782853&amp;dn=ShesAFreak+-+Ashley+Reeves&amp;tr=udp%3A%2F%2Ftracker.openbittorrent.com%3A80&amp;tr=udp%3A%2F%2Fopen.demonii.com%3A1337&amp;tr=udp%3A%2F%2Ftracker.coppersurfer.tk%3A6969&amp;tr=udp%3A%2F%2Fexodus.desync.com%3A6969","seeders":0,"leechers":1,"uploader":"Rabiner","files":3,"time":1315866793,"description":"ShesAFreak - Ashley Reeves wmv\n\n\n &lt;a href=&quot;\nhttp://www.imagesnake.com/img/14172/1.jpg&quot; rel=&quot;nofollow&quot; target=&quot;_NEW&quot;&gt;\nhttp://www.imagesnake.com/img/14172/1.jpg&lt;/a&gt; \n &lt;a href=&quot;\nhttp://www.imagesnake.com/img/14173/pic.jpg&quot; rel=&quot;nofollow&quot; target=&quot;_NEW&quot;&gt;\nhttp://www.imagesnake.com/img/14173/pic.jpg&lt;/a&gt; ","torrent":{"xt":"urn:btih:4a3ae397d795b170e2e911cf230e0400be782853","amp;dn":"ShesAFreak+-+Ashley+Reeves","amp;tr":["udp%3A%2F%2Ftracker.openbittorrent.com%3A80","udp%3A%2F%2Fopen.demonii.com%3A1337","udp%3A%2F%2Ftracker.coppersurfer.tk%3A6969","udp%3A%2F%2Fexodus.desync.com%3A6969"],"infoHash":"4a3ae397d795b170e2e911cf230e0400be782853","infoHashBuffer":{"type":"Buffer","data":[74,58,227,151,215,149,177,112,226,233,17,207,35,14,4,0,190,120,40,83]},"announce":[],"urlList":[]}}