{"title":"5 inch Floppy s02e21 Magic The Gathering Special hdtv h264-5if [","uid":6670252,"size":341831944,"categoryP":"video","categoryS":"tv_shows","magnet":"?xt=urn:btih:5bbba64f0eaae49dc6cf6fd1a5f650014cfc2ef4&amp;dn=5+inch+Floppy+s02e21+Magic+The+Gathering+Special+hdtv+h264-5if+%5B&amp;tr=udp%3A%2F%2Ftracker.openbittorrent.com%3A80&amp;tr=udp%3A%2F%2Fopen.demonii.com%3A1337&amp;tr=udp%3A%2F%2Ftracker.coppersurfer.tk%3A6969&amp;tr=udp%3A%2F%2Fexodus.desync.com%3A6969","seeders":0,"leechers":0,"uploader":"eztv","files":1,"time":1315846572,"description":"#EZTV @ EFNet -&gt; To avoid fakes, ALWAYS check that the torrent was added by eztv. &lt;a href=&quot;\nhttp://eztv.it/&quot; rel=&quot;nofollow&quot; target=&quot;_NEW&quot;&gt;\nhttp://eztv.it/&lt;/a&gt;\n\nEpisode: 5 inch Floppy s02e21 Magic The Gathering Special hdtv h264-5if\nScreenshots:\n\n\n\n\nWant to help us out? BitCoin: 1Fw4sRdZYFwULfeE7oQ91GLYKy8j5EcuFW","torrent":{"xt":"urn:btih:5bbba64f0eaae49dc6cf6fd1a5f650014cfc2ef4","amp;dn":"5+inch+Floppy+s02e21+Magic+The+Gathering+Special+hdtv+h264-5if+%5B","amp;tr":["udp%3A%2F%2Ftracker.openbittorrent.com%3A80","udp%3A%2F%2Fopen.demonii.com%3A1337","udp%3A%2F%2Ftracker.coppersurfer.tk%3A6969","udp%3A%2F%2Fexodus.desync.com%3A6969"],"infoHash":"5bbba64f0eaae49dc6cf6fd1a5f650014cfc2ef4","infoHashBuffer":{"type":"Buffer","data":[91,187,166,79,14,170,228,157,198,207,111,209,165,246,80,1,76,252,46,244]},"announce":[],"urlList":[]}}