{"title":"GinTonic","uid":6663318,"size":67170653,"categoryP":"audio","categoryS":"music","magnet":"?xt=urn:btih:607fbe26d5c2c30f0c951d131e794ebdfb9376db&amp;dn=GinTonic&amp;tr=udp%3A%2F%2Ftracker.openbittorrent.com%3A80&amp;tr=udp%3A%2F%2Fopen.demonii.com%3A1337&amp;tr=udp%3A%2F%2Ftracker.coppersurfer.tk%3A6969&amp;tr=udp%3A%2F%2Fexodus.desync.com%3A6969","seeders":0,"leechers":0,"uploader":"timekilla","files":-1,"time":1315596051,"description":"Artist...............: Various Artists\nAlbum................: GinTonic\nGenre................: NuJazz/House\nVersion..............: MPEG 1 Layer III\nQuality..............: CBR, (avg. bitrate: 320kbps)\nChannels.............: Stereo / 44100 hz\n\n\n\nTracklisting :\n\nPalais mascotte - rollercone\n\nFreetempo - Incidental Montage\n\nkruder &amp; dorfmeister - jazz master \n\nParov Stelar - Super Eight\n\nTosca - Honey (Faze Action Dub)\n\nVariety Lab - london in the rain\n\nCan - Cruisin\\\\\\\\\\\\\\\\\\\\\\\\\\\\\\'\n\nMassive Attack - Weather Storm\n\nThunderball - Angela\\\\\\\\\\\\\\\\\\\\\\\\\\\\\\'s Lament\n\nTosca - Rolf Royce\n\n\nTotal Size...........:64.0 MB","torrent":{"xt":"urn:btih:607fbe26d5c2c30f0c951d131e794ebdfb9376db","amp;dn":"GinTonic","amp;tr":["udp%3A%2F%2Ftracker.openbittorrent.com%3A80","udp%3A%2F%2Fopen.demonii.com%3A1337","udp%3A%2F%2Ftracker.coppersurfer.tk%3A6969","udp%3A%2F%2Fexodus.desync.com%3A6969"],"infoHash":"607fbe26d5c2c30f0c951d131e794ebdfb9376db","infoHashBuffer":{"type":"Buffer","data":[96,127,190,38,213,194,195,15,12,149,29,19,30,121,78,189,251,147,118,219]},"announce":[],"urlList":[]}}