{"title":"bbwsgoneblack.com - Samantha 38G - Puppy Love - 35 min","uid":6547279,"size":820259432,"categoryP":"porn","categoryS":"movie_clips","magnet":"?xt=urn:btih:6b6eb147adf039ea7459fbdb4236bdef0c3bce41&amp;dn=bbwsgoneblack.com+-+Samantha+38G+-+Puppy+Love+-+35+min&amp;tr=udp%3A%2F%2Ftracker.openbittorrent.com%3A80&amp;tr=udp%3A%2F%2Fopen.demonii.com%3A1337&amp;tr=udp%3A%2F%2Ftracker.coppersurfer.tk%3A6969&amp;tr=udp%3A%2F%2Fexodus.desync.com%3A6969","seeders":0,"leechers":0,"uploader":"bestec1234","files":-1,"time":1310920285,"description":"Additional Screenshots:\n &lt;a href=&quot;\nhttp://www.imagebam.com/gallery/fifazxp40uqj50tfkmdc4yd61mqam2gt/&quot; rel=&quot;nofollow&quot; target=&quot;_NEW&quot;&gt;\nhttp://www.imagebam.com/gallery/fifazxp40uqj50tfkmdc4yd61mqam2gt/&lt;/a&gt;\n\n\n\n\nDownload the photoset here:\n &lt;a href=&quot;\nhttp://thepiratebay.se/torrent/6547274/bbwsgoneblack.com_-_Samantha_38G_-_Puppy_Love_-_455_pics&quot; rel=&quot;nofollow&quot; target=&quot;_NEW&quot;&gt;\nhttp://thepiratebay.se/torrent/6547274/bbwsgoneblack.com_-_Samantha_38G_-_Puppy_Love_-_455_pics&lt;/a&gt;","torrent":{"xt":"urn:btih:6b6eb147adf039ea7459fbdb4236bdef0c3bce41","amp;dn":"bbwsgoneblack.com+-+Samantha+38G+-+Puppy+Love+-+35+min","amp;tr":["udp%3A%2F%2Ftracker.openbittorrent.com%3A80","udp%3A%2F%2Fopen.demonii.com%3A1337","udp%3A%2F%2Ftracker.coppersurfer.tk%3A6969","udp%3A%2F%2Fexodus.desync.com%3A6969"],"infoHash":"6b6eb147adf039ea7459fbdb4236bdef0c3bce41","infoHashBuffer":{"type":"Buffer","data":[107,110,177,71,173,240,57,234,116,89,251,219,66,54,189,239,12,59,206,65]},"announce":[],"urlList":[]}}