{"title":"Case.Histories.S01E03.Subtitulado.Español.SC.avi","uid":7354467,"size":577720320,"categoryP":"video","categoryS":"tv_shows","magnet":"?xt=urn:btih:899868a5813bfddb88fca6bbf0c4de9fdee54993&amp;dn=Case.Histories.S01E03.Subtitulado.Espa%26ntilde%3Bol.SC.avi&amp;tr=udp%3A%2F%2Ftracker.openbittorrent.com%3A80&amp;tr=udp%3A%2F%2Fopen.demonii.com%3A1337&amp;tr=udp%3A%2F%2Ftracker.coppersurfer.tk%3A6969&amp;tr=udp%3A%2F%2Fexodus.desync.com%3A6969","seeders":0,"leechers":2,"uploader":"ffcantero","files":1,"time":1339714032,"description":"cold case BBC","torrent":{"xt":"urn:btih:899868a5813bfddb88fca6bbf0c4de9fdee54993","amp;dn":"Case.Histories.S01E03.Subtitulado.Espa%26ntilde%3Bol.SC.avi","amp;tr":["udp%3A%2F%2Ftracker.openbittorrent.com%3A80","udp%3A%2F%2Fopen.demonii.com%3A1337","udp%3A%2F%2Ftracker.coppersurfer.tk%3A6969","udp%3A%2F%2Fexodus.desync.com%3A6969"],"infoHash":"899868a5813bfddb88fca6bbf0c4de9fdee54993","infoHashBuffer":{"type":"Buffer","data":[137,152,104,165,129,59,253,219,136,252,166,187,240,196,222,159,222,229,73,147]},"announce":[],"urlList":[]}}