{"title":"AllOver30.Patris.XXX.720p.WMV-YAPG","uid":7300816,"size":286753329,"categoryP":"porn","categoryS":"movie_clips","magnet":"?xt=urn:btih:90694b176d8df39c1532b0a8ad97cd46967f846d&amp;dn=AllOver30.Patris.XXX.720p.WMV-YAPG&amp;tr=udp%3A%2F%2Ftracker.openbittorrent.com%3A80&amp;tr=udp%3A%2F%2Fopen.demonii.com%3A1337&amp;tr=udp%3A%2F%2Ftracker.coppersurfer.tk%3A6969&amp;tr=udp%3A%2F%2Fexodus.desync.com%3A6969","seeders":0,"leechers":0,"uploader":"digital_ripper","files":1,"time":1337991069,"description":"cover\n &lt;a href=&quot;\nhttp://sexseeimage.com/showpic-735/26.05.12allover30___patris.jpg&quot; rel=&quot;nofollow&quot; target=&quot;_NEW&quot;&gt;\nhttp://sexseeimage.com/showpic-735/26.05.12allover30___patris.jpg&lt;/a&gt;\n\n\npreview\n &lt;a href=&quot;\nhttp://sexseeimage.com/showpic-736/26.05.12allover30.patris.xxx.720p.wmv_yapg_s.jpg&quot; rel=&quot;nofollow&quot; target=&quot;_NEW&quot;&gt;\nhttp://sexseeimage.com/showpic-736/26.05.12allover30.patris.xxx.720p.wmv_yapg_s.jpg&lt;/a&gt;","torrent":{"xt":"urn:btih:90694b176d8df39c1532b0a8ad97cd46967f846d","amp;dn":"AllOver30.Patris.XXX.720p.WMV-YAPG","amp;tr":["udp%3A%2F%2Ftracker.openbittorrent.com%3A80","udp%3A%2F%2Fopen.demonii.com%3A1337","udp%3A%2F%2Ftracker.coppersurfer.tk%3A6969","udp%3A%2F%2Fexodus.desync.com%3A6969"],"infoHash":"90694b176d8df39c1532b0a8ad97cd46967f846d","infoHashBuffer":{"type":"Buffer","data":[144,105,75,23,109,141,243,156,21,50,176,168,173,151,205,70,150,127,132,109]},"announce":[],"urlList":[]}}