{"title":"Bridesmaids.2011.CUSTOM.SWESUB.NTSC.DVDR-nOoneKnoWs","uid":6663055,"size":4678032405,"categoryP":"video","categoryS":"movies_dvdr","magnet":"?xt=urn:btih:924125181d014eef5b7484934128c99faa5fa511&amp;dn=Bridesmaids.2011.CUSTOM.SWESUB.NTSC.DVDR-nOoneKnoWs&amp;tr=udp%3A%2F%2Ftracker.openbittorrent.com%3A80&amp;tr=udp%3A%2F%2Fopen.demonii.com%3A1337&amp;tr=udp%3A%2F%2Ftracker.coppersurfer.tk%3A6969&amp;tr=udp%3A%2F%2Fexodus.desync.com%3A6969","seeders":0,"leechers":0,"uploader":"SnowCrash03","files":-1,"time":1315588530,"description":"Bridesmaids.2011.CUSTOM.SWESUB.NTSC.DVDR-nOoneKnoWs\n\n\n\nRelease Date...... 2011-09-09\n\n\n\nRars.............. 93x50\n\n\n\nImg Size.......... 4,31 GB\n\n\n\nPlayTime.......... 125 min\n\n\n\nIMDb.............. http://www.imdb.com/title/tt1478338/\n\n\n\nGenre............. Comedy\n\n\n\nSource............ Bridesmaids.720p.BluRay.x264-REFiNED\n\n\n\nVideo............. Converted to DVD, Avg. Bitrate ca 4 191 kbps\n\n\n\nAudio............. ENG 5.1\n\n\n\nSub............... SWE\n\n\n\nMenu.............. Custom\n\n\n\nKontakt........... &lt;a class=&quot;__cf_email__&quot; href=&quot;/cdn-cgi/l/email-protection&quot; data-cfemail=&quot;89e7e6e6e6e7ece2e7e6fefac9e1fcfae1e4e8e0e5a7eae6e4&quot;&gt;[email&amp;#160;protected]&lt;/a&gt;&lt;script data-cfhash='f9e31' type=&quot;text/javascript&quot;&gt;\n/* &lt;![CDATA[ */!function(){try{var t=&quot;currentScript&quot;in document?document.currentScript:function(){for(var t=document.getElementsByTagName(&quot;script&quot;),e=t.length;e--;)if(t[e].getAttribute(&quot;data-cfhash&quot;))return t[e]}();if(t&amp;&amp;t.previousSibling){var e,r,n,i,c=t.previousSibling,a=c.getAttribute(&quot;data-cfemail&quot;);if(a){for(e=&quot;&quot;,r=parseInt(a.substr(0,2),16),n=2;a.length-n;n+=2)i=parseInt(a.substr(n,2),16)^r,e+=String.fromCharCode(i);e=document.createTextNode(e),c.parentNode.replaceChild(e,c)}t.parentNode.removeChild(t);}}catch(u){}}()/* ]]&gt; */&lt;/script&gt;\n\n\n\nnotes............. -\n\n\nAnnies liv ÃƒÂ¤r en enda rÃƒÂ¶ra. Men nÃƒÂ¤r hon fÃƒÂ¥r reda pÃƒÂ¥ att hennes bÃƒÂ¤sta vÃƒÂ¤n Lillian ÃƒÂ¤r fÃƒÂ¶rlovad mÃƒÂ¥ste hon bara tacka ja till att vara brudtÃƒÂ¤rna. Trots att hon ÃƒÂ¤r bÃƒÂ¥de pank och singel bluffar sig Annie genom bÃƒÂ¥de dyra och bisarra ritualer. Med bara en chans att fÃƒÂ¥ det rÃƒÂ¤tt kommer Annie att visa Lillian och hennes tÃƒÂ¤rnor exakt hur lÃƒÂ¥ngt nÃƒÂ¥gon ÃƒÂ¤r beredd att gÃƒÂ¥ fÃƒÂ¶r sin bÃƒÂ¤sta vÃƒÂ¤n.","torrent":{"xt":"urn:btih:924125181d014eef5b7484934128c99faa5fa511","amp;dn":"Bridesmaids.2011.CUSTOM.SWESUB.NTSC.DVDR-nOoneKnoWs","amp;tr":["udp%3A%2F%2Ftracker.openbittorrent.com%3A80","udp%3A%2F%2Fopen.demonii.com%3A1337","udp%3A%2F%2Ftracker.coppersurfer.tk%3A6969","udp%3A%2F%2Fexodus.desync.com%3A6969"],"infoHash":"924125181d014eef5b7484934128c99faa5fa511","infoHashBuffer":{"type":"Buffer","data":[146,65,37,24,29,1,78,239,91,116,132,147,65,40,201,159,170,95,165,17]},"announce":[],"urlList":[]}}