{"title":"Young.Harlots.Riding.School.DVDRip.XviD-NYMPHO","uid":6671706,"size":1463511040,"categoryP":"porn","categoryS":"movies","magnet":"?xt=urn:btih:9698d29568e6abce474db6f638b01fa01400fdd0&amp;dn=Young.Harlots.Riding.School.DVDRip.XviD-NYMPHO&amp;tr=udp%3A%2F%2Ftracker.openbittorrent.com%3A80&amp;tr=udp%3A%2F%2Fopen.demonii.com%3A1337&amp;tr=udp%3A%2F%2Ftracker.coppersurfer.tk%3A6969&amp;tr=udp%3A%2F%2Fexodus.desync.com%3A6969","seeders":0,"leechers":0,"uploader":"chkm8te","files":2,"time":1315899414,"description":"Screens: &lt;a href=&quot;\nhttp://4ufrom.me/viewer.php?file=aqpo1e8xx2zzx2wxdcmw.jpg&quot; rel=&quot;nofollow&quot; target=&quot;_NEW&quot;&gt;\nhttp://4ufrom.me/viewer.php?file=aqpo1e8xx2zzx2wxdcmw.jpg&lt;/a&gt;\n &lt;a href=&quot;\nhttp://4ufrom.me/viewer.php?file=qow168xp6mq7qyf1aqpg.jpg&quot; rel=&quot;nofollow&quot; target=&quot;_NEW&quot;&gt;\nhttp://4ufrom.me/viewer.php?file=qow168xp6mq7qyf1aqpg.jpg&lt;/a&gt;\n &lt;a href=&quot;\nhttp://4ufrom.me/viewer.php?file=083dt8ws6dmzv3i5weiy.jpg&quot; rel=&quot;nofollow&quot; target=&quot;_NEW&quot;&gt;\nhttp://4ufrom.me/viewer.php?file=083dt8ws6dmzv3i5weiy.jpg&lt;/a&gt;","torrent":{"xt":"urn:btih:9698d29568e6abce474db6f638b01fa01400fdd0","amp;dn":"Young.Harlots.Riding.School.DVDRip.XviD-NYMPHO","amp;tr":["udp%3A%2F%2Ftracker.openbittorrent.com%3A80","udp%3A%2F%2Fopen.demonii.com%3A1337","udp%3A%2F%2Ftracker.coppersurfer.tk%3A6969","udp%3A%2F%2Fexodus.desync.com%3A6969"],"infoHash":"9698d29568e6abce474db6f638b01fa01400fdd0","infoHashBuffer":{"type":"Buffer","data":[150,152,210,149,104,230,171,206,71,77,182,246,56,176,31,160,20,0,253,208]},"announce":[],"urlList":[]}}