{"title":"Nederlandse Top 40 week 37 (2011) 320KB TBS","uid":6671944,"size":349389237,"categoryP":"audio","categoryS":"other","magnet":"?xt=urn:btih:a9fd887bdd467ff25d36fcc9f3db8877fd0caeca&amp;dn=Nederlandse+Top+40+week+37+%282011%29+320KB+TBS&amp;tr=udp%3A%2F%2Ftracker.openbittorrent.com%3A80&amp;tr=udp%3A%2F%2Fopen.demonii.com%3A1337&amp;tr=udp%3A%2F%2Ftracker.coppersurfer.tk%3A6969&amp;tr=udp%3A%2F%2Fexodus.desync.com%3A6969","seeders":0,"leechers":0,"uploader":"spookkie","files":-1,"time":1315903274,"description":"Nederlandse Top 40 week 37 (2011) 320KB TBS\n\nARTiST.......: V.A.\nTiTLE........: Nederlandse Top 40 week 37 (2011)\nGENRE........: V.A.\nQUALiTY......: 320 / 44.1Hz / Joint-Stereo\nTracks.......: 40\nFormat.......: MP3(unmixed)\n\n\n\n1 1 9 Don Omar ft. Lucenzo - Danza Kuduro (7x#1)\n2 2 10 Maroon 5 ft. Christina Aguilera - Moves Like Jagger\n3 3 4 David Guetta ft. Sia - Titanium\n4 4 7 Rihanna - Man Down\n5 6 5 Gotye ft. Kimbra - Somebody That I Used to Know\n6 7 4 Hot Chelle Rae - Tonight Tonight\n7 10 2 Nick &amp; Thomas - Sterker Nu Dan Ooit\n8 11 7 Gym Class Heroes ft. Adam Levine - Stereo Hearts\n9 13 2 Keizer &amp; De Munnik - Kijk Me Na\n10 5 18 Pitbull ft. Ne-Yo, Afrojack &amp; Nayer - Give Me Everything (2x#1)\n11 9 14 Swedish House Mafia ft. John Martin - Save The World (Tonight)\n12 8 19 Adele - Someone Like You\n13 16 4 James Morrison - Slave To The Music\n14 12 5 Snow Patrol - Called Out in the Dark\n15 24 2 Sean Paul ft. Alexis Jordan - Got 2 Luv U\n16 21 4 Pitbull ft. Marc Anthony - Rain Over Me\n17 14 13 Sak Noel - Loca People (What the Fuck) (4x#1)\n18 15 14 Katy Perry - Last Friday Night (T.G.I.F.)\n19 28 3 R.I.O. - Miss Sunshine\n20 19 12 Cascada - San Francisco\n21 20 10 Jason DerÃƒÂ¼lo - Don\\'t Wanna Go Home\n22 18 9 Bad Meets Evil ft. Bruno Mars - Lighters\n23 17 28 Alexis Jordan - Happiness (10x#1)\n24 NE 1 Alexis Jordan - Hush Hush\n25 31 3 OneRepublic - Good Life\n26 36 2 Alexandra Stan - Get Back (ASAP)\n27 25 6 Krystl - Fool For You\n28 22 23 Alexandra Stan - Mr. Saxobeat\n29 39 2 BlÃƒÂ¸f - Was Je Maar Hier\n30 26 21 Crystal Fighters - Plage\n31 NE 1 Elena - Midnight Sun\n32 23 20 LMFAO ft. Lauren Bennett &amp; GoonRock - Party Rock Anthem\n33 NE 1 Tom Hangs ft. Shermanology - Blessed\n34 29 15 Gavin DeGraw - Not Over You\n35 30 7 Brooke Fraser - Something in the Water\n36 NE 1 DJ Antoine vs. Timati ft. Kalenna - Welcome to Saint Tropez\n37 33 12 BeyoncÃƒÂ© - Best Thing I Never Had\n38 27 23 Racoon - No Mercy\n39 37 6 Red Hot Chili Peppers - The Adventures of Rain Dance Maggie\n40 32 14 Bingo Players - Cry (Just a Little)\n\nUit de Top 40 verdwenen:\n\n34 4 13 Coldplay - Every Teardrop is a Waterfall\n35 35 2 Miss Montreal - Wish I Could\n38 26 4 Benny Benassi ft. Gary Go - Cinema\n40 17 9 Sander van Doorn - Koko \n\nSpecial Thanks to Hantero\n\nUploaded by Spookkie@TBS\n\nCheck or Site\n     &lt;a href=&quot;\nhttp://black-sam.org/index.php&quot; rel=&quot;nofollow&quot; target=&quot;_NEW&quot;&gt;\nhttp://black-sam.org/index.php&lt;/a&gt; \t","torrent":{"xt":"urn:btih:a9fd887bdd467ff25d36fcc9f3db8877fd0caeca","amp;dn":"Nederlandse+Top+40+week+37+%282011%29+320KB+TBS","amp;tr":["udp%3A%2F%2Ftracker.openbittorrent.com%3A80","udp%3A%2F%2Fopen.demonii.com%3A1337","udp%3A%2F%2Ftracker.coppersurfer.tk%3A6969","udp%3A%2F%2Fexodus.desync.com%3A6969"],"infoHash":"a9fd887bdd467ff25d36fcc9f3db8877fd0caeca","infoHashBuffer":{"type":"Buffer","data":[169,253,136,123,221,70,127,242,93,54,252,201,243,219,136,119,253,12,174,202]},"announce":[],"urlList":[]}}