{"title":"Kaydara 2011 BRRIP XVID-WBZ","uid":7221332,"size":784117029,"categoryP":"video","categoryS":"movies","magnet":"?xt=urn:btih:af5a39601a2a1073b7f3daf356e7880adcacec92&amp;dn=Kaydara+2011+BRRIP+XVID-WBZ&amp;tr=udp%3A%2F%2Ftracker.openbittorrent.com%3A80&amp;tr=udp%3A%2F%2Fopen.demonii.com%3A1337&amp;tr=udp%3A%2F%2Ftracker.coppersurfer.tk%3A6969&amp;tr=udp%3A%2F%2Fexodus.desync.com%3A6969","seeders":0,"leechers":1,"uploader":"boobsman","files":-1,"time":1335535973,"description":"THIS IS A FAN FILM NOT AN OFFICIAL MATRIX MOVIE!\n\nKaydara 2011 BRRIP XVID-WBZ\n\nPLOT:\nThis story takes place in the universe of the Wachowski brothers' film '\nThe Matrix'. Kaydara, a bounty hunter who is living separately from the \nHuman Resistance Group, does not believe in the prophecy of the 'chosen \none' . He thinks this 'saviour' is a threat to the awakening of Man's \nself-awareness. He considers the 'chosen one' as his enemy and if they \ncross paths, will not hesitate to confront him.\n\nDETAILS:\nSource: Russian bluray \nGenre: Action | Sci-Fi \nLength: 00:55:09 \nRatings: 6.5/10 from 52 users   \nIMDb: http://www.imdb.com/title/tt1869509/\n\nVIDEO:\nCodec: XviD\nBit Rate: 1615 kbps\nResolution: 704x298\nAspect Ratio: 2.35:1\nFrame Rate: 25 fps \n\nAUDIO:\nCodec: AC3\nBit Rate: 224Kbps\nChannels: 6 Channles \nLanguage: English \nSubs: None \n &lt;a href=&quot;\nhttp://www.freeimage.us/image-8F13_4F9A8858.jpg&quot; rel=&quot;nofollow&quot; target=&quot;_NEW&quot;&gt;\nhttp://www.freeimage.us/image-8F13_4F9A8858.jpg&lt;/a&gt; &lt;a href=&quot;\nhttp://www.freeimage.us/image-0916_4F9A8858.jpg&quot; rel=&quot;nofollow&quot; target=&quot;_NEW&quot;&gt;\nhttp://www.freeimage.us/image-0916_4F9A8858.jpg&lt;/a&gt; &lt;a href=&quot;\nhttp://www.freeimage.us/image-EC82_4F9A88E5.jpg&quot; rel=&quot;nofollow&quot; target=&quot;_NEW&quot;&gt;\nhttp://www.freeimage.us/image-EC82_4F9A88E5.jpg&lt;/a&gt; &lt;a href=&quot;\nhttp://www.freeimage.us/image-C264_4F9A88E5.jpg&quot; rel=&quot;nofollow&quot; target=&quot;_NEW&quot;&gt;\nhttp://www.freeimage.us/image-C264_4F9A88E5.jpg&lt;/a&gt;","torrent":{"xt":"urn:btih:af5a39601a2a1073b7f3daf356e7880adcacec92","amp;dn":"Kaydara+2011+BRRIP+XVID-WBZ","amp;tr":["udp%3A%2F%2Ftracker.openbittorrent.com%3A80","udp%3A%2F%2Fopen.demonii.com%3A1337","udp%3A%2F%2Ftracker.coppersurfer.tk%3A6969","udp%3A%2F%2Fexodus.desync.com%3A6969"],"infoHash":"af5a39601a2a1073b7f3daf356e7880adcacec92","infoHashBuffer":{"type":"Buffer","data":[175,90,57,96,26,42,16,115,183,243,218,243,86,231,136,10,220,172,236,146]},"announce":[],"urlList":[]}}