{"title":"Ten Little Piggies 8 - Sandra Kalerman.avi","uid":7389774,"size":187590164,"categoryP":"porn","categoryS":"movie_clips","magnet":"?xt=urn:btih:b925a951f1798d448fe3bca2ec8925ee51a64090&amp;dn=Ten+Little+Piggies+8+-+Sandra+Kalerman.avi&amp;tr=udp%3A%2F%2Ftracker.openbittorrent.com%3A80&amp;tr=udp%3A%2F%2Fopen.demonii.com%3A1337&amp;tr=udp%3A%2F%2Ftracker.coppersurfer.tk%3A6969&amp;tr=udp%3A%2F%2Fexodus.desync.com%3A6969","seeders":0,"leechers":1,"uploader":"1.No.1","files":-1,"time":1340739000,"description":"Ten Little Piggies 8 - Sandra Kalerman.avi\n\n2006, All Sex, Oral, Footjob, Fetish, Hardcore, XXX, Adult\n\n512 x 384\n\n00:23:38\n\n178.90 MB\n\nScreens\n &lt;a href=&quot;\nhttp://www.pixsor.com/share-629D_4FE9F309.html&quot; rel=&quot;nofollow&quot; target=&quot;_NEW&quot;&gt;\nhttp://www.pixsor.com/share-629D_4FE9F309.html&lt;/a&gt;\n &lt;a href=&quot;\nhttp://www.pixsor.com/share-6EB7_4FE9F309.html&quot; rel=&quot;nofollow&quot; target=&quot;_NEW&quot;&gt;\nhttp://www.pixsor.com/share-6EB7_4FE9F309.html&lt;/a&gt;","torrent":{"xt":"urn:btih:b925a951f1798d448fe3bca2ec8925ee51a64090","amp;dn":"Ten+Little+Piggies+8+-+Sandra+Kalerman.avi","amp;tr":["udp%3A%2F%2Ftracker.openbittorrent.com%3A80","udp%3A%2F%2Fopen.demonii.com%3A1337","udp%3A%2F%2Ftracker.coppersurfer.tk%3A6969","udp%3A%2F%2Fexodus.desync.com%3A6969"],"infoHash":"b925a951f1798d448fe3bca2ec8925ee51a64090","infoHashBuffer":{"type":"Buffer","data":[185,37,169,81,241,121,141,68,143,227,188,162,236,137,37,238,81,166,64,144]},"announce":[],"urlList":[]}}