{"title":"The Avengers - United They Stand - 1999 - Episode 3.avi","uid":7384201,"size":135083566,"categoryP":"video","categoryS":"tv_shows","magnet":"?xt=urn:btih:c296f51f5cdc7f4dcd43743b3bf50e82eb03d5ee&amp;dn=The+Avengers+-+United+They+Stand+-+1999+-+Episode+3.avi&amp;tr=udp%3A%2F%2Ftracker.openbittorrent.com%3A80&amp;tr=udp%3A%2F%2Fopen.demonii.com%3A1337&amp;tr=udp%3A%2F%2Ftracker.coppersurfer.tk%3A6969&amp;tr=udp%3A%2F%2Fexodus.desync.com%3A6969","seeders":0,"leechers":0,"uploader":"J-RedtheRed","files":-1,"time":1340582865,"description":"The Avengers: United They Stand (also known simply as The Avengers) is an animated series based on the Marvel Comics superhero team The Avengers. It consists of 13 episodes, which originally premiered on October 30, 1999, and was produced by Avi Arad and distributed by 20th Century Fox Television. It was later canceled on February 26, 2000.\n \nThe series features a team based on the roster for the 1984 The West Coast Avengers, composed of Ant-Man, the Wasp, Wonder Man, Tigra, Hawkeye, the Vision, and Scarlet Witch.\n\n","torrent":{"xt":"urn:btih:c296f51f5cdc7f4dcd43743b3bf50e82eb03d5ee","amp;dn":"The+Avengers+-+United+They+Stand+-+1999+-+Episode+3.avi","amp;tr":["udp%3A%2F%2Ftracker.openbittorrent.com%3A80","udp%3A%2F%2Fopen.demonii.com%3A1337","udp%3A%2F%2Ftracker.coppersurfer.tk%3A6969","udp%3A%2F%2Fexodus.desync.com%3A6969"],"infoHash":"c296f51f5cdc7f4dcd43743b3bf50e82eb03d5ee","infoHashBuffer":{"type":"Buffer","data":[194,150,245,31,92,220,127,77,205,67,116,59,59,245,14,130,235,3,213,238]},"announce":[],"urlList":[]}}