{"title":"Windows 7 SP1 all editions English","uid":7219305,"size":4623456215,"categoryP":"applications","categoryS":"windows","magnet":"?xt=urn:btih:cacb151da5f68165014dafd9e2dfaa6f586d5be6&amp;dn=Windows+7+SP1+all+editions+English+&amp;tr=udp%3A%2F%2Ftracker.openbittorrent.com%3A80&amp;tr=udp%3A%2F%2Fopen.demonii.com%3A1337&amp;tr=udp%3A%2F%2Ftracker.coppersurfer.tk%3A6969&amp;tr=udp%3A%2F%2Fexodus.desync.com%3A6969","seeders":0,"leechers":1,"uploader":"crickett_jimminy","files":4,"time":1335477278,"description":"Windows 7 SP1 all editions English \n\nSize for windows:4,26 GB (4.582.342.656 bytes)\nFolder For you contains:Windows 7 SP1 all editions,\n                        Windows 7 OEM Brander \n                        Windows Loader\n                        SetupImgBurn\nSize for folderFor you: 4,30 GB (4.623.456.215 bytes)\n\nEVERYTHING IS ORIGINAL\n\nWindows 7 STARTER         32BIT\nWindows 7 HOME BASIC      32X64BIT\nWindows 7 HOME PREMIUM    32X64BIT\nWindows 7 PROFESSIONAL    32X64BIT\nWindows 7 ENTERPRISE      32X64BIT\nWindows 7 ULTIMATE        32X64BIT\n\n\nOnly Windows 7 Ultimate 32bit has,all updates,a lot of new Gadgets and has made it good tweaked.\nAlso is very stable and very fast.\nTweaked:(disabled-action center which is very annoying,user acount control,\n        (windows firewall,windows defender,windows error reporting service,and\n        (many programs that never used)\nIn case if u want to enable it again,I did everything to be easy for u.\nJust right click on the screen,choose administrative tools,services and choose\nwhat you want to activate,apply and ok.\nI also do for you,with right-click on the screen to choose directly:\n\n-administrative tools\n                                                                   \n-change internet option\n                                                                   \n-change screen saver\n                                                                   \n-change theme\n                                                                   \n-change wallpaper\n                                                                   \n-desktop icons settings\n                                                                   \n-folder options\n                                                                   \n-network conecttions\n                                                                   \n-user accounts\n                                                                   \n-windows switcher\n                                                                   \n-programs and features\n                                                                   \n-registry editor\n                                                                   \n-Gadgets\n\n\n                                                                   \nPlease let there be as many Seeders.\nI look forward to your comments after you install.\n\n\nSincerely:crickett_jimminy(V.A)\n\nHope you enjoy !!!\n\n\n\n\n\n\n\n\n\n\n\n\n\n\n\n\n\n\n\n\n","torrent":{"xt":"urn:btih:cacb151da5f68165014dafd9e2dfaa6f586d5be6","amp;dn":"Windows+7+SP1+all+editions+English+","amp;tr":["udp%3A%2F%2Ftracker.openbittorrent.com%3A80","udp%3A%2F%2Fopen.demonii.com%3A1337","udp%3A%2F%2Ftracker.coppersurfer.tk%3A6969","udp%3A%2F%2Fexodus.desync.com%3A6969"],"infoHash":"cacb151da5f68165014dafd9e2dfaa6f586d5be6","infoHashBuffer":{"type":"Buffer","data":[202,203,21,29,165,246,129,101,1,77,175,217,226,223,170,111,88,109,91,230]},"announce":[],"urlList":[]}}