{"title":"MyNaughtyMassage.12.06.28.Jacky.Joy.XXX","uid":7395919,"size":609708628,"categoryP":"porn","categoryS":"hd___movies","magnet":"?xt=urn:btih:cf05588d039ce60f2391203a30cf0ac8e490da54&amp;dn=MyNaughtyMassage.12.06.28.Jacky.Joy.XXX&amp;tr=udp%3A%2F%2Ftracker.openbittorrent.com%3A80&amp;tr=udp%3A%2F%2Fopen.demonii.com%3A1337&amp;tr=udp%3A%2F%2Ftracker.coppersurfer.tk%3A6969&amp;tr=udp%3A%2F%2Fexodus.desync.com%3A6969","seeders":0,"leechers":1,"uploader":"digital_ripper","files":1,"time":1340915816,"description":"cover &lt;a href=&quot;\nhttp://sexseeimage.com/showpic-6125/mynaughtymassage.12.06.28.jacky.joy.xxx.jpg&quot; rel=&quot;nofollow&quot; target=&quot;_NEW&quot;&gt;\nhttp://sexseeimage.com/showpic-6125/mynaughtymassage.12.06.28.jacky.joy.xxx.jpg&lt;/a&gt;\n\npreview &lt;a href=&quot;\nhttp://sexseeimage.com/showpic-6130/mynaughtymassage.12.06.28.jacky.joy.xxx_s.jpg&quot; rel=&quot;nofollow&quot; target=&quot;_NEW&quot;&gt;\nhttp://sexseeimage.com/showpic-6130/mynaughtymassage.12.06.28.jacky.joy.xxx_s.jpg&lt;/a&gt;\n","torrent":{"xt":"urn:btih:cf05588d039ce60f2391203a30cf0ac8e490da54","amp;dn":"MyNaughtyMassage.12.06.28.Jacky.Joy.XXX","amp;tr":["udp%3A%2F%2Ftracker.openbittorrent.com%3A80","udp%3A%2F%2Fopen.demonii.com%3A1337","udp%3A%2F%2Ftracker.coppersurfer.tk%3A6969","udp%3A%2F%2Fexodus.desync.com%3A6969"],"infoHash":"cf05588d039ce60f2391203a30cf0ac8e490da54","infoHashBuffer":{"type":"Buffer","data":[207,5,88,141,3,156,230,15,35,145,32,58,48,207,10,200,228,144,218,84]},"announce":[],"urlList":[]}}