{"title":"[Trance] DJ Feel - TranceMission (24-04-2012)","uid":7230173,"size":136812792,"categoryP":"audio","categoryS":"music","magnet":"?xt=urn:btih:cf88d61bd8f4f56d685306c54174b9fe60ed2b6d&amp;dn=%5BTrance%5D+DJ+Feel+-+TranceMission+%2824-04-2012%29&amp;tr=udp%3A%2F%2Ftracker.openbittorrent.com%3A80&amp;tr=udp%3A%2F%2Fopen.demonii.com%3A1337&amp;tr=udp%3A%2F%2Ftracker.coppersurfer.tk%3A6969&amp;tr=udp%3A%2F%2Fexodus.desync.com%3A6969","seeders":0,"leechers":0,"uploader":"promoparty","files":-1,"time":1335809289,"description":"=============================================================================\n\nDJ Feel - TranceMission (24-04-2012)\n\nGenre: Progressive Trance, Uplifting Trance\nDate: 24-04-2012\nFormat: 320 kbps\nSite: http://www.djfeel.net\n\n01. Paul van Dyk feat Austin Leeds - Symmetries [VANDIT]\n02. Gareth Emery Feat. Christina Novelli - Concrete Angel (Original Mix) [GARUDA]\n03. Estiva &amp; Tania Zygar - Death Of Me (Original Mix) [ENHANCED]\n04. Paul van Dyk feat Arty - The Ocean [VANDIT]\n05. Daniel Kandi - Insert Generic Title (Daniel Kandi vs Dennis Pedersen Remix) [ENHANCED]\n06. Dennis Sheperd, Alan Morris feat. Sue McLaren - I Die (Album Extended Mix) [HIGH CONTRAST]\n07. Broning - Reinspired (Original Mix) [DIGITAL SOCIETY]\n08. Speed Limits - Bris (Colonial One Remix) [ENHANCED]\n09. Alexander Popov - Attractive Force (Original Mix) [ASOT]\n10. Ralphie B - Icarus (Original Mix) [ASOT]\n11. Sean Tyas feat David Berkeley - Take My Hand (John Ocallaghan Remix) [SUBCULTURE]\n12. The Thrillseekers - Synaesthesia (Paul van Dyk Remix) [VANDIT]\n\n==========================================================\nDownload or subscribe to free podcast episodes from DJ FEEL on iTunes!  &lt;a href=&quot;\nhttp://itunes.apple.com/podcast/id441099329&quot; rel=&quot;nofollow&quot; target=&quot;_NEW&quot;&gt;\nhttp://itunes.apple.com/podcast/id441099329&lt;/a&gt;\n=========================================================","torrent":{"xt":"urn:btih:cf88d61bd8f4f56d685306c54174b9fe60ed2b6d","amp;dn":"%5BTrance%5D+DJ+Feel+-+TranceMission+%2824-04-2012%29","amp;tr":["udp%3A%2F%2Ftracker.openbittorrent.com%3A80","udp%3A%2F%2Fopen.demonii.com%3A1337","udp%3A%2F%2Ftracker.coppersurfer.tk%3A6969","udp%3A%2F%2Fexodus.desync.com%3A6969"],"infoHash":"cf88d61bd8f4f56d685306c54174b9fe60ed2b6d","infoHashBuffer":{"type":"Buffer","data":[207,136,214,27,216,244,245,109,104,83,6,197,65,116,185,254,96,237,43,109]},"announce":[],"urlList":[]}}