{"title":"Deep Purple - Bombay Live '95.ISO","uid":7277194,"size":4647376896,"categoryP":"video","categoryS":"tv_shows","magnet":"?xt=urn:btih:d5fb50f500cc337cfedb65b1f1bc013d9b62b4e9&amp;dn=Deep+Purple+-+Bombay+Live+%2795.ISO&amp;tr=udp%3A%2F%2Ftracker.openbittorrent.com%3A80&amp;tr=udp%3A%2F%2Fopen.demonii.com%3A1337&amp;tr=udp%3A%2F%2Ftracker.coppersurfer.tk%3A6969&amp;tr=udp%3A%2F%2Fexodus.desync.com%3A6969","seeders":0,"leechers":5,"uploader":"Ezequielmafra","files":1,"time":1337323618,"description":"DVD5","torrent":{"xt":"urn:btih:d5fb50f500cc337cfedb65b1f1bc013d9b62b4e9","amp;dn":"Deep+Purple+-+Bombay+Live+%2795.ISO","amp;tr":["udp%3A%2F%2Ftracker.openbittorrent.com%3A80","udp%3A%2F%2Fopen.demonii.com%3A1337","udp%3A%2F%2Ftracker.coppersurfer.tk%3A6969","udp%3A%2F%2Fexodus.desync.com%3A6969"],"infoHash":"d5fb50f500cc337cfedb65b1f1bc013d9b62b4e9","infoHashBuffer":{"type":"Buffer","data":[213,251,80,245,0,204,51,124,254,219,101,177,241,188,1,61,155,98,180,233]},"announce":[],"urlList":[]}}