{"title":"National.Geographic.Birth.Of.Europe.Part.3.Fire.HDTV.XviD-AFG","uid":7210528,"size":396732431,"categoryP":"video","categoryS":"tv_shows","magnet":"?xt=urn:btih:dc4ecdf0e3aba4c8161f382522706b852524126f&amp;dn=National.Geographic.Birth.Of.Europe.Part.3.Fire.HDTV.XviD-AFG&amp;tr=udp%3A%2F%2Ftracker.openbittorrent.com%3A80&amp;tr=udp%3A%2F%2Fopen.demonii.com%3A1337&amp;tr=udp%3A%2F%2Ftracker.coppersurfer.tk%3A6969&amp;tr=udp%3A%2F%2Fexodus.desync.com%3A6969","seeders":0,"leechers":1,"uploader":"TvTeam","files":4,"time":1335223141,"description":".  TD Sign UP is open. so you better hurry up ;) ENJOYYY!!!!     (^_~)  \n  &lt;a href=&quot;\nhttp://www.torrentday.com&quot; rel=&quot;nofollow&quot; target=&quot;_NEW&quot;&gt;\nhttp://www.torrentday.com&lt;/a&gt;\n\n\nTo Avoid Fakes, ALWAYS Check That The Torrent Was Added By: TvTeam.\n\n\n               www . TorrentDay . Com \n(((((((((((((= Enjoy No RAR releases =))))))))))))))))))))\n\n...................................NFO:....................................\n\nEnjoy our Fast Upload.\nFor more info about this release, open .NFO file with notepad :)","torrent":{"xt":"urn:btih:dc4ecdf0e3aba4c8161f382522706b852524126f","amp;dn":"National.Geographic.Birth.Of.Europe.Part.3.Fire.HDTV.XviD-AFG","amp;tr":["udp%3A%2F%2Ftracker.openbittorrent.com%3A80","udp%3A%2F%2Fopen.demonii.com%3A1337","udp%3A%2F%2Ftracker.coppersurfer.tk%3A6969","udp%3A%2F%2Fexodus.desync.com%3A6969"],"infoHash":"dc4ecdf0e3aba4c8161f382522706b852524126f","infoHashBuffer":{"type":"Buffer","data":[220,78,205,240,227,171,164,200,22,31,56,37,34,112,107,133,37,36,18,111]},"announce":[],"urlList":[]}}