{"title":"Sexy Girls undressed &amp; XX 150 Pictures [Up to 3000 Px]part5","uid":6669426,"size":19350864,"categoryP":"other","categoryS":"pictures","magnet":"?xt=urn:btih:e899de32c3a28f86fed5917519fc2f9826122d98&amp;dn=Sexy+Girls+undressed+%26amp%3B+XX+150+Pictures+%5BUp+to+3000+Px%5Dpart5&amp;tr=udp%3A%2F%2Ftracker.openbittorrent.com%3A80&amp;tr=udp%3A%2F%2Fopen.demonii.com%3A1337&amp;tr=udp%3A%2F%2Ftracker.coppersurfer.tk%3A6969&amp;tr=udp%3A%2F%2Fexodus.desync.com%3A6969","seeders":0,"leechers":0,"uploader":"ShihanMihiranga","files":1,"time":1315819420,"description":"Sexy Girls undressed &amp; XXX 150 Pictures\n &amp; XXX Pictures 150  Wallpapers{2000 x 3000} mixed resolution \n\n\n\nsee inside some naughty ones also included \n\n\nneed more of this Photos  use my Tpb Url download other Parts \n\n    &lt;a href=&quot;\nhttp://thepiratebay.se/user/ShihanMihiranga/&quot; rel=&quot;nofollow&quot; target=&quot;_NEW&quot;&gt;\nhttp://thepiratebay.se/user/ShihanMihiranga/&lt;/a&gt;\n\n\nSample Pictures\n\n &lt;a href=&quot;\nhttp://freeimage.uphero.com/?v=2284.jpg&quot; rel=&quot;nofollow&quot; target=&quot;_NEW&quot;&gt;\nhttp://freeimage.uphero.com/?v=2284.jpg&lt;/a&gt;\n &lt;a href=&quot;\nhttp://freeimage.uphero.com/?v=2336.jpg&quot; rel=&quot;nofollow&quot; target=&quot;_NEW&quot;&gt;\nhttp://freeimage.uphero.com/?v=2336.jpg&lt;/a&gt;\n &lt;a href=&quot;\nhttp://freeimage.uphero.com/?v=2258.jpg&quot; rel=&quot;nofollow&quot; target=&quot;_NEW&quot;&gt;\nhttp://freeimage.uphero.com/?v=2258.jpg&lt;/a&gt;\n &lt;a href=&quot;\nhttp://freeimage.uphero.com/?v=2259.jpg&quot; rel=&quot;nofollow&quot; target=&quot;_NEW&quot;&gt;\nhttp://freeimage.uphero.com/?v=2259.jpg&lt;/a&gt;","torrent":{"xt":"urn:btih:e899de32c3a28f86fed5917519fc2f9826122d98","amp;dn":"Sexy+Girls+undressed+%26amp%3B+XX+150+Pictures+%5BUp+to+3000+Px%5Dpart5","amp;tr":["udp%3A%2F%2Ftracker.openbittorrent.com%3A80","udp%3A%2F%2Fopen.demonii.com%3A1337","udp%3A%2F%2Ftracker.coppersurfer.tk%3A6969","udp%3A%2F%2Fexodus.desync.com%3A6969"],"infoHash":"e899de32c3a28f86fed5917519fc2f9826122d98","infoHashBuffer":{"type":"Buffer","data":[232,153,222,50,195,162,143,134,254,213,145,117,25,252,47,152,38,18,45,152]},"announce":[],"urlList":[]}}