{"title":"Madness Live At Rock City Nottingham 07.12.2010 Bootleg.avi","uid":6666059,"size":1296662190,"categoryP":"video","categoryS":"music_videos","magnet":"?xt=urn:btih:f8f7f1fd1200286feac9f397e15ba3e99e2c5419&amp;dn=Madness+Live+At+Rock+City+Nottingham+07.12.2010+Bootleg.avi&amp;tr=udp%3A%2F%2Ftracker.openbittorrent.com%3A80&amp;tr=udp%3A%2F%2Fopen.demonii.com%3A1337&amp;tr=udp%3A%2F%2Ftracker.coppersurfer.tk%3A6969&amp;tr=udp%3A%2F%2Fexodus.desync.com%3A6969","seeders":0,"leechers":0,"uploader":"chakaone","files":1,"time":1315686439,"description":"this is a repost to the original file which was uploaded\n\nenjoy the concert\n\nvideo 6 outta 10\n\naudio 4 outta 10\n\ndecent copy of the whole concert please comment.\n\n","torrent":{"xt":"urn:btih:f8f7f1fd1200286feac9f397e15ba3e99e2c5419","amp;dn":"Madness+Live+At+Rock+City+Nottingham+07.12.2010+Bootleg.avi","amp;tr":["udp%3A%2F%2Ftracker.openbittorrent.com%3A80","udp%3A%2F%2Fopen.demonii.com%3A1337","udp%3A%2F%2Ftracker.coppersurfer.tk%3A6969","udp%3A%2F%2Fexodus.desync.com%3A6969"],"infoHash":"f8f7f1fd1200286feac9f397e15ba3e99e2c5419","infoHashBuffer":{"type":"Buffer","data":[248,247,241,253,18,0,40,111,234,201,243,151,225,91,163,233,158,44,84,25]},"announce":[],"urlList":[]}}