{"title":"Cuck0ld 6.avi","uid":7222456,"size":730348646,"categoryP":"porn","categoryS":"movies","magnet":"?xt=urn:btih:fb1296f719b47887ec5411b42a46f27b26f49a45&amp;dn=Cuck0ld+6.avi&amp;tr=udp%3A%2F%2Ftracker.openbittorrent.com%3A80&amp;tr=udp%3A%2F%2Fopen.demonii.com%3A1337&amp;tr=udp%3A%2F%2Ftracker.coppersurfer.tk%3A6969&amp;tr=udp%3A%2F%2Fexodus.desync.com%3A6969","seeders":0,"leechers":0,"uploader":"merzedes","files":1,"time":1335565793,"description":"Cuck0ld 6.avi\n\nScreens  ","torrent":{"xt":"urn:btih:fb1296f719b47887ec5411b42a46f27b26f49a45","amp;dn":"Cuck0ld+6.avi","amp;tr":["udp%3A%2F%2Ftracker.openbittorrent.com%3A80","udp%3A%2F%2Fopen.demonii.com%3A1337","udp%3A%2F%2Ftracker.coppersurfer.tk%3A6969","udp%3A%2F%2Fexodus.desync.com%3A6969"],"infoHash":"fb1296f719b47887ec5411b42a46f27b26f49a45","infoHashBuffer":{"type":"Buffer","data":[251,18,150,247,25,180,120,135,236,84,17,180,42,70,242,123,38,244,154,69]},"announce":[],"urlList":[]}}