{"title":"Desi Teen Anitha sucking Fucking her lover &amp; enjoying his co","uid":6685079,"size":14186991,"categoryP":"porn","categoryS":"movie_clips","magnet":"?xt=urn:btih:fc0a34162c977e551d3a3e1fa428df5b0b050829&amp;dn=Desi+Teen+Anitha+sucking+Fucking+her+lover+%26amp%3B+enjoying+his+co&amp;tr=udp%3A%2F%2Ftracker.openbittorrent.com%3A80&amp;tr=udp%3A%2F%2Fopen.demonii.com%3A1337&amp;tr=udp%3A%2F%2Ftracker.coppersurfer.tk%3A6969&amp;tr=udp%3A%2F%2Fexodus.desync.com%3A6969","seeders":0,"leechers":1,"uploader":"vantank","files":1,"time":1316372542,"description":"Desi Teen Anitha sucking Fucking her lover &amp; enjoying his cock with nice sexy expressions\n\nSample Screens :\n\n~~~~~~~~~~~~~~~~~~~~~~~~~~~~~~~~~~~~~~~~~~~~~~~~~~~~~~~~~~~~~~~~~~~~~~~\n &lt;a href=&quot;\nhttp://landa.6te.net/?iview=1316365190.jpg&quot; rel=&quot;nofollow&quot; target=&quot;_NEW&quot;&gt;\nhttp://landa.6te.net/?iview=1316365190.jpg&lt;/a&gt;\n\n~~~~~~~~~~~~~~~~~~~~~~~~~~~~~~~~~~~~~~~~~~~~~~~~~~~~~~~~~~~~~~~~~~~~~~~\t","torrent":{"xt":"urn:btih:fc0a34162c977e551d3a3e1fa428df5b0b050829","amp;dn":"Desi+Teen+Anitha+sucking+Fucking+her+lover+%26amp%3B+enjoying+his+co","amp;tr":["udp%3A%2F%2Ftracker.openbittorrent.com%3A80","udp%3A%2F%2Fopen.demonii.com%3A1337","udp%3A%2F%2Ftracker.coppersurfer.tk%3A6969","udp%3A%2F%2Fexodus.desync.com%3A6969"],"infoHash":"fc0a34162c977e551d3a3e1fa428df5b0b050829","infoHashBuffer":{"type":"Buffer","data":[252,10,52,22,44,151,126,85,29,58,62,31,164,40,223,91,11,5,8,41]},"announce":[],"urlList":[]}}